pixell/__init__.py
pixell/cli/__init__.py
pixell/cli/main.py
pixell/cli/commands/__init__.py
pixell/cli/commands/agent.py
pixell/cli/commands/config.py
pixell/cli/commands/deploy.py
pixell/cli/commands/guide.py
pixell/cli/commands/intent.py
pixell/cli/commands/registry.py
pixell/cli/commands/secrets.py
pixell/cli/commands/test.py
pixell/cli/commands/ui.py
pixell/core/__init__.py
pixell/core/builder.py
pixell/core/deployment.py
pixell/core/registry.py
pixell/core/secrets.py
pixell/core/secrets_utils.py
pixell/core/validator.py
pixell/dev_server/__init__.py
pixell/dev_server/server.py
pixell/intent/__init__.py
pixell/intent/models.py
pixell/intent/policy.py
pixell/intent/rate_limit.py
pixell/intent/validate.py
pixell/models/__init__.py
pixell/models/agent_manifest.py
pixell/models/capability.py
pixell/protocol/__init__.py
pixell/protocol/ui_messages.py
pixell/protocol/validate.py
pixell/protocol/schemas/action.result.schema.json
pixell/protocol/schemas/ui.event.schema.json
pixell/protocol/schemas/ui.patch.schema.json
pixell/sdk/__init__.py
pixell/sdk/context.py
pixell/sdk/data_client.py
pixell/sdk/errors.py
pixell/sdk/oauth.py
pixell/sdk/progress.py
pixell/sdk/server.py
pixell/sdk/task_consumer.py
pixell/sdk/a2a/__init__.py
pixell/sdk/a2a/client.py
pixell/sdk/a2a/handlers.py
pixell/sdk/a2a/protocol.py
pixell/sdk/a2a/streaming.py
pixell/sdk/plan_mode/__init__.py
pixell/sdk/plan_mode/agent.py
pixell/sdk/plan_mode/context.py
pixell/sdk/plan_mode/events.py
pixell/sdk/plan_mode/phases.py
pixell/sdk/plan_mode/ui.py
pixell/sdk/tool_mode/__init__.py
pixell/sdk/tool_mode/agent.py
pixell/sdk/translation/__init__.py
pixell/sdk/translation/context.py
pixell/sdk/translation/interface.py
pixell/test/__init__.py
pixell/test/test_runner.py
pixell/tools/__init__.py
pixell/tools/file_tools.py
pixell/tools/presentation/__init__.py
pixell/tools/presentation/base.py
pixell/tools/presentation/guidance.py
pixell/tools/presentation/standard.py
pixell/tools/presentation/domains/__init__.py
pixell_sdk-0.4.30.dist-info/licenses/LICENSE
pixell_sdk-0.4.30.dist-info/METADATA
pixell_sdk-0.4.30.dist-info/WHEEL
pixell_sdk-0.4.30.dist-info/entry_points.txt
pixell_sdk-0.4.30.dist-info/top_level.txt
pixell_sdk-0.4.30.dist-info/RECORD
