Metadata-Version: 2.4
Name: pixell-sdk
Version: 0.4.30
Summary: A lightweight developer kit for packaging AI agents into portable APKG files
Home-page: https://github.com/pixell-global/pixell-kit
Author: Pixell Core Team
Author-email: Pixell Core Team <dev@pixell.global>
License-Expression: AGPL-3.0-only
Project-URL: Homepage, https://github.com/pixell-global/pixell-kit
Project-URL: Bug Tracker, https://github.com/pixell-global/pixell-kit/issues
Project-URL: Documentation, https://docs.pixell.global/pixell
Project-URL: Source Code, https://github.com/pixell-global/pixell-kit
Classifier: Development Status :: 3 - Alpha
Classifier: Intended Audience :: Developers
Classifier: Topic :: Software Development :: Build Tools
Classifier: Programming Language :: Python :: 3
Classifier: Programming Language :: Python :: 3.11
Classifier: Programming Language :: Python :: 3.12
Classifier: Operating System :: OS Independent
Requires-Python: >=3.11
License-File: LICENSE
Requires-Dist: click>=8.0
Requires-Dist: pydantic>=2.0
Requires-Dist: pyyaml>=6.0
Requires-Dist: jsonschema>=4.0
Requires-Dist: fastapi>=0.100.0
Requires-Dist: uvicorn>=0.23.0
Requires-Dist: watchdog>=3.0
Requires-Dist: python-dotenv>=1.0
Requires-Dist: tabulate>=0.9
Requires-Dist: jinja2>=3.0
Requires-Dist: requests>=2.28.0
Requires-Dist: redis>=5.0.0
Requires-Dist: httpx>=0.25.0
Requires-Dist: pyjwt>=2.8.0
Provides-Extra: dev
Requires-Dist: pytest>=7.0; extra == "dev"
Requires-Dist: pytest-cov>=4.0; extra == "dev"
Requires-Dist: pytest-asyncio>=0.21; extra == "dev"
Requires-Dist: black>=23.0; extra == "dev"
Requires-Dist: mypy>=1.0; extra == "dev"
Requires-Dist: ruff>=0.1; extra == "dev"
Requires-Dist: build>=1.0; extra == "dev"
Requires-Dist: twine>=4.0; extra == "dev"
Requires-Dist: types-PyYAML>=6.0; extra == "dev"
Requires-Dist: fakeredis>=2.20.0; extra == "dev"
Requires-Dist: respx>=0.20.0; extra == "dev"
Requires-Dist: pytest-timeout>=2.0; extra == "dev"
Provides-Extra: signing
Requires-Dist: python-gnupg>=0.5; extra == "signing"
Dynamic: author
Dynamic: home-page
Dynamic: license-file
Dynamic: requires-python
